aerospike_vector/__init__.py
aerospike_vector/auth_pb2.py
aerospike_vector/auth_pb2_grpc.py
aerospike_vector/conversions.py
aerospike_vector/index_pb2.py
aerospike_vector/index_pb2_grpc.py
aerospike_vector/transact_pb2.py
aerospike_vector/transact_pb2_grpc.py
aerospike_vector/types.py
aerospike_vector/types_pb2.py
aerospike_vector/types_pb2_grpc.py
aerospike_vector/vector_db_pb2.py
aerospike_vector/vector_db_pb2_grpc.py
aerospike_vector/vectordb_admin.py
aerospike_vector/vectordb_channel_provider.py
aerospike_vector/vectordb_client.py
aerospike_vector-0.4.0.dist-info/LICENSE
aerospike_vector-0.4.0.dist-info/METADATA
aerospike_vector-0.4.0.dist-info/WHEEL
aerospike_vector-0.4.0.dist-info/top_level.txt
aerospike_vector-0.4.0.dist-info/RECORD
