Metadata-Version: 2.1
Name: aerospike-vector
Version: 0.4.0
Summary: Aerospike Proximus Client Library for Python
Author-email: "Aerospike, Inc." <info@aerospike.com>
License: Apache Software License
Project-URL: Homepage, https://aerospike.com
Keywords: aerospike,vector,database,ANN
Classifier: License :: OSI Approved :: Apache Software License
Classifier: Operating System :: POSIX :: Linux
Classifier: Operating System :: MacOS :: MacOS X
Classifier: Programming Language :: Python :: 3.8
Classifier: Programming Language :: Python :: 3.9
Classifier: Programming Language :: Python :: 3.10
Classifier: Programming Language :: Python :: 3.11
Classifier: Programming Language :: Python :: Implementation :: CPython
Classifier: Topic :: Database
Requires-Python: >3.8
License-File: LICENSE
Requires-Dist: grpcio
Requires-Dist: protobuf
